gcvspline/__init__.py
gcvspline/_gcvspl.pyd
gcvspline/gcvspline.py
gcvspline/gcvspline2.py
gcvspline/.libs/libgcvspl.NL7FKJNT7ONLJQC7MIR3YVQRQRDTYSCQ.gfortran-win32.dll
gcvspline/tests/__init__.py
gcvspline/tests/test_gcvspline.py
gcvspline/tests/test_gcvspline2.py
gcvspline-0.4.dist-info/LICENSE
gcvspline-0.4.dist-info/METADATA
gcvspline-0.4.dist-info/WHEEL
gcvspline-0.4.dist-info/top_level.txt
gcvspline-0.4.dist-info/RECORD
