Metadata-Version: 2.1
Name: gcvspline
Version: 0.4
Summary: A Python wrapper for gcvspl.f, a FORTRAN package for generalized, cross-validatory spline smoothing and differentiation.
Home-page: https://github.com/charlesll/gcvspline
Author: Charles Le Losq and Yu Feng
Author-email: charles.lelosq@anu.edu.au
License: GNU-GPLv3
Platform: UNKNOWN
Requires-Dist: numpy (>=1.12)
